{"cameraMode":{"drawMode":0,"name":"Shaded","section":"Shading Mode"},"sceneLighting":true,"audioPlay":false,"sceneViewState":{"m_AlwaysRefresh":false,"showFog":true,"showSkybox":true,"showFlares":true,"showImageEffects":true,"showParticleSystems":true,"showVisualEffectGraphs":true,"m_FxEnabled":true},"in2DMode":false,"pivot":{"x":47.14162063598633,"y":-7.767243385314941,"z":22.852386474609376},"rotation":{"x":-0.22949588298797608,"y":-0.29873374104499819,"z":0.07424858957529068,"w":-0.9233540892601013},"size":19.281116485595704,"orthographic":false}